
{
  "ID": 234,
  "Name": "Unorthodox Valley",
  "Resource Location": "blue_skies:unorthodox_valley",
  "Class": "com.legacy.blue_skies.world.everdawn.biome.BiomeUnorthodoxValley",
  "Root Height": 0.2,
  "Height Variation": 0.7,
  "Top Block": "blue_skies:lunar_grass[home_dim\u003dtrue,snowy\u003dfalse]",
  "Filler Block": "blue_skies:lunar_dirt",
  "Ocean Top Block": "Disabled. Activate in BiomeTweakerCore.",
  "Ocean Filler Block": "Disabled. Activate in BiomeTweakerCore.",
  "Actual Filler Blocks": "Disabled. Activate in BiomeTweakerCore.",
  "Grass Color": "Disabled. Activate in BiomeTweakerCore.",
  "Foliage Color": "Disabled. Activate in BiomeTweakerCore.",
  "Water Color": "65431",
  "Temperature": 0.5,
  "Humidity": 0.5,
  "Water Tint": 65431,
  "Enable Rain": true,
  "Enable Snow": false,
  "Dictionary Types": [
    "MAGICAL",
    "MOUNTAIN",
    "HILLS"
  ],
  "BiomeManager Entries": {},
  "Spawnable Creatures": [
    {
      "Entity Class": "com.legacy.blue_skies.entities.passive.EntityCosmicFox",
      "Weight": 30,
      "Min Group Count": 2,
      "Max Group Count": 3
    },
    {
      "Entity Class": "com.legacy.blue_skies.entities.neutral.EntityNightshadeBear",
      "Weight": 10,
      "Min Group Count": 2,
      "Max Group Count": 4
    }
  ],
  "Spawnable Monsters": [
    {
      "Entity Class": "net.minecraft.entity.monster.EntityWitch",
      "Weight": 1,
      "Min Group Count": 1,
      "Max Group Count": 1
    },
    {
      "Entity Class": "com.legacy.blue_skies.entities.hostile.EntityVenomSpider",
      "Weight": 20,
      "Min Group Count": 1,
      "Max Group Count": 1
    }
  ],
  "Spawnable Water Creatures": [],
  "Spawnable Cave Creatures": [],
  "Spawn Biome": false,
  "Tweaked": false,
  "BOP Generators": {
    "FLOWERS Generators": [
      {
        "ID": "flora",
        "Name": "glowshrooms"
      },
      {
        "ID": "flora",
        "Name": "miners_delight"
      },
      {
        "ID": "flora",
        "Name": "roots"
      }
    ]
  },
  "BOP Owner": "OTHER",
  "BOP Weight Map": {},
  "BOP Climate Weights": {},
  "BOP Island Weight": 0
}