<galaxy>
    <star name="Arcturus (K1.5III)" temp="100" x="0" y="0" size="1.8" numPlanets="0" numGasGiants="0" blackHole="false">
        <star name="Arcturus-test" size="3" temp="120" separation="20"></star>
        <planet name="Glacidus" DIMID="4" dimMapping="" customIcon="glacidus">
            <isKnown>true</isKnown>
            <hasRings>true</hasRings>
            <atmosphereDensity>80</atmosphereDensity>
            <hasOxygen>true</hasOxygen>
            <gravitationalMultiplier>50</gravitationalMultiplier>
            <orbitalDistance>70</orbitalDistance>
            <orbitalTheta>120</orbitalTheta>
            <orbitalPhi>10</orbitalPhi>
            <rotationalPeriod>24771</rotationalPeriod>
            <planet name="Mining Site 495-IIM" DIMID="0" customIcon="asteroid">
        	   <isKnown>true</isKnown>
               <genType>2</genType>
               <atmosphereDensity>0</atmosphereDensity>
               <gravitationalMultiplier>5</gravitationalMultiplier>
               <orbitalDistance>80</orbitalDistance>
               <orbitalTheta>48</orbitalTheta>
               <orbitalPhi>63</orbitalPhi>
               <biomeIds>advancedrocketry:space</biomeIds>
               <fillerBlock></fillerBlock>
               <OreGen></OreGen>
               <oceanBlock></oceanBlock>
               <seaLevel></seaLevel>
               <rotationalPeriod>11525</rotationalPeriod>
            </planet>
        </planet>
        <planet name="Ring World" DIMID="18" dimMapping="" customIcon="earthlike">
            <isKnown>true</isKnown>
            <hasRings>false</hasRings>
            <atmosphereDensity>100</atmosphereDensity>
            <gravitationalMultiplier>100</gravitationalMultiplier>
            <orbitalDistance>25</orbitalDistance>
            <orbitalTheta>90</orbitalTheta>
            <orbitalPhi>90</orbitalPhi>
            <rotationalPeriod>2147483647</rotationalPeriod>        
        </planet>
    </star>
</galaxy>